game_werewolf/__init__.py
game_werewolf/blocks.py
game_werewolf/game_werewolf.py
game_werewolf/example/werewolf.yaml
chatgpt_mirai_qq_bot_game_werewolf-0.3.5.dist-info/LICENSE
chatgpt_mirai_qq_bot_game_werewolf-0.3.5.dist-info/METADATA
chatgpt_mirai_qq_bot_game_werewolf-0.3.5.dist-info/WHEEL
chatgpt_mirai_qq_bot_game_werewolf-0.3.5.dist-info/entry_points.txt
chatgpt_mirai_qq_bot_game_werewolf-0.3.5.dist-info/top_level.txt
chatgpt_mirai_qq_bot_game_werewolf-0.3.5.dist-info/RECORD
